consensusgen/__init__.py
consensusgen/consensusGen.py
consensusgen-2.8.dist-info/licenses/LICENCE.md
consensusgen-2.8.dist-info/METADATA
consensusgen-2.8.dist-info/WHEEL
consensusgen-2.8.dist-info/top_level.txt
consensusgen-2.8.dist-info/RECORD
