Metadata-Version: 2.4
Name: consensusGen
Version: 2.8
Summary: Genetic algorithm for consensus building
Home-page: https://pypi.org/project/consensusGen/
Author: RomainCoulon (Romain Coulon)
Author-email: <romain.coulon@bipm.org>
Project-URL: Documentation, https://github.com/RomainCoulon/consensusGen/
Keywords: genetic algorithm,inter-laboratory comparison,consenus building
Classifier: Development Status :: 4 - Beta
Classifier: Intended Audience :: Science/Research
Classifier: License :: OSI Approved :: MIT License
Classifier: Natural Language :: English
Classifier: Natural Language :: French
Classifier: Programming Language :: Python :: 3
Classifier: Operating System :: Unix
Classifier: Operating System :: MacOS :: MacOS X
Classifier: Operating System :: Microsoft :: Windows
Classifier: Topic :: Scientific/Engineering :: Physics
License-File: LICENCE.md
Requires-Dist: numpy
Requires-Dist: matplotlib
Dynamic: author
Dynamic: author-email
Dynamic: classifier
Dynamic: description
Dynamic: description-content-type
Dynamic: home-page
Dynamic: keywords
Dynamic: license-file
Dynamic: project-url
Dynamic: requires-dist
Dynamic: summary
